{
  "type": "FeatureCollection",
  "features": [
    {
      "type": "Feature",
      "properties": {
        "name": "Starconch"
      },
      "geometry": {
        "type": "Point",
        "coordinates": [
          13.886719,
          -55.329144
        ]
      }
    },
    {
      "type": "Feature",
      "properties": {
        "name": "Starconch"
      },
      "geometry": {
        "type": "Point",
        "coordinates": [
          13.447266,
          -53.514185
        ]
      }
    },
    {
      "type": "Feature",
      "properties": {
        "name": "Starconch"
      },
      "geometry": {
        "type": "Point",
        "coordinates": [
          11.865234,
          -53.852527
        ]
      }
    },
    {
      "type": "Feature",
      "properties": {
        "name": "Starconch"
      },
      "geometry": {
        "type": "Point",
        "coordinates": [
          11.337891,
          -52.696361
        ]
      }
    },
    {
      "type": "Feature",
      "properties": {
        "name": "Starconch"
      },
      "geometry": {
        "type": "Point",
        "coordinates": [
          9.624023,
          -54.41893
        ]
      }
    },
    {
      "type": "Feature",
      "properties": {
        "name": "Starconch"
      },
      "geometry": {
        "type": "Point",
        "coordinates": [
          12.128906,
          -56.632064
        ]
      }
    },
    {
      "type": "Feature",
      "properties": {
        "name": "Starconch"
      },
      "geometry": {
        "type": "Point",
        "coordinates": [
          14.238281,
          -57.751076
        ]
      }
    },
    {
      "type": "Feature",
      "properties": {
        "name": "Starconch"
      },
      "geometry": {
        "type": "Point",
        "coordinates": [
          15.336914,
          -55.998381
        ]
      }
    },
    {
      "type": "Feature",
      "properties": {
        "name": "Starconch"
      },
      "geometry": {
        "type": "Point",
        "coordinates": [
          7.69043,
          -51.069017
        ]
      }
    },
    {
      "type": "Feature",
      "properties": {
        "name": "Starconch"
      },
      "geometry": {
        "type": "Point",
        "coordinates": [
          6.240234,
          -51.124213
        ]
      }
    },
    {
      "type": "Feature",
      "properties": {
        "name": "Starconch"
      },
      "geometry": {
        "type": "Point",
        "coordinates": [
          5.668945,
          -49.61071
        ]
      }
    },
    {
      "type": "Feature",
      "properties": {
        "name": "Starconch"
      },
      "geometry": {
        "type": "Point",
        "coordinates": [
          4.042969,
          -49.781264
        ]
      }
    },
    {
      "type": "Feature",
      "properties": {
        "name": "Starconch"
      },
      "geometry": {
        "type": "Point",
        "coordinates": [
          3.735352,
          -49.496675
        ]
      }
    },
    {
      "type": "Feature",
      "properties": {
        "name": "Starconch"
      },
      "geometry": {
        "type": "Point",
        "coordinates": [
          3.647461,
          -48.980217
        ]
      }
    },
    {
      "type": "Feature",
      "properties": {
        "name": "Starconch"
      },
      "geometry": {
        "type": "Point",
        "coordinates": [
          2.636719,
          -47.15984
        ]
      }
    },
    {
      "type": "Feature",
      "properties": {
        "name": "Starconch"
      },
      "geometry": {
        "type": "Point",
        "coordinates": [
          2.329102,
          -44.621754
        ]
      }
    },
    {
      "type": "Feature",
      "properties": {
        "name": "Starconch"
      },
      "geometry": {
        "type": "Point",
        "coordinates": [
          3.515625,
          -43.452919
        ]
      }
    },
    {
      "type": "Feature",
      "properties": {
        "name": "Starconch"
      },
      "geometry": {
        "type": "Point",
        "coordinates": [
          5.097656,
          -42.293564
        ]
      }
    },
    {
      "type": "Feature",
      "properties": {
        "name": "Starconch"
      },
      "geometry": {
        "type": "Point",
        "coordinates": [
          5.625,
          -42.972502
        ]
      }
    },
    {
      "type": "Feature",
      "properties": {
        "name": "Starconch"
      },
      "geometry": {
        "type": "Point",
        "coordinates": [
          5.009766,
          -40.044438
        ]
      }
    }
  ]
}